[
  {
    "line": 2,
    "elements": [
      {
        "line": 4,
        "name": "",
        "description": "",
        "type": "background",
        "keyword": "Background",
        "steps": [
          {
            "result": {
              "duration": 999800,
              "status": "skipped"
            },
            "line": 5,
            "name": "User is on Retail website",
            "match": {
              "location": "step.definitions.DesktopStepDef.user_is_on_retail_website()"
            },
            "keyword": "Given "
          },
          {
            "result": {
              "status": "skipped"
            },
            "line": 6,
            "name": "User click on Desktops tab",
            "match": {
              "location": "step.definitions.DesktopStepDef.user_click_on_desktops_tab()"
            },
            "keyword": "When "
          },
          {
            "result": {
              "duration": 1000200,
              "status": "skipped"
            },
            "line": 7,
            "name": "User click on Show all desktops",
            "match": {
              "location": "step.definitions.DesktopStepDef.user_click_on_show_all_desktops()"
            },
            "keyword": "And "
          }
        ]
      },
      {
        "start_timestamp": "2022-05-05T04:06:51.487Z",
        "before": [
          {
            "result": {
              "error_message": "java.lang.NullPointerException: Cannot invoke \"String.hashCode()\" because the return value of \"core.Base.getBrowser()\" is null\r\n\tat core.Base.selectBrowser(Base.java:63)\r\n\tat step.definitions.Initializer.beforeHooks(Initializer.java:19)\r\n",
              "duration": 94452300,
              "status": "failed"
            },
            "match": {
              "location": "step.definitions.Initializer.beforeHooks(io.cucumber.java.Scenario)"
            }
          }
        ],
        "line": 10,
        "name": "User verify all items are present in Desktops tab",
        "description": "",
        "id": "desktops;user-verify-all-items-are-present-in-desktops-tab",
        "after": [
          {
            "result": {
              "error_message": "java.lang.NullPointerException: Cannot invoke \"org.openqa.selenium.WebDriver.close()\" because \"core.Base.driver\" is null\r\n\tat core.Base.tearDown(Base.java:58)\r\n\tat step.definitions.Initializer.afterHooks(Initializer.java:27)\r\n",
              "status": "failed"
            },
            "match": {
              "location": "step.definitions.Initializer.afterHooks(io.cucumber.java.Scenario)"
            }
          }
        ],
        "type": "scenario",
        "keyword": "Scenario",
        "steps": [
          {
            "result": {
              "status": "skipped"
            },
            "line": 11,
            "name": "User should see all items are present in Desktop page",
            "match": {
              "location": "step.definitions.DesktopStepDef.user_should_see_all_items_are_present_in_desktop_page()"
            },
            "keyword": "Then "
          }
        ],
        "tags": [
          {
            "name": "@TestAllDesktops"
          },
          {
            "name": "@DesktopItemPresense"
          }
        ]
      },
      {
        "line": 4,
        "name": "",
        "description": "",
        "type": "background",
        "keyword": "Background",
        "steps": [
          {
            "result": {
              "duration": 999400,
              "status": "skipped"
            },
            "line": 5,
            "name": "User is on Retail website",
            "match": {
              "location": "step.definitions.DesktopStepDef.user_is_on_retail_website()"
            },
            "keyword": "Given "
          },
          {
            "result": {
              "status": "skipped"
            },
            "line": 6,
            "name": "User click on Desktops tab",
            "match": {
              "location": "step.definitions.DesktopStepDef.user_click_on_desktops_tab()"
            },
            "keyword": "When "
          },
          {
            "result": {
              "status": "skipped"
            },
            "line": 7,
            "name": "User click on Show all desktops",
            "match": {
              "location": "step.definitions.DesktopStepDef.user_click_on_show_all_desktops()"
            },
            "keyword": "And "
          }
        ]
      },
      {
        "start_timestamp": "2022-05-05T04:06:51.668Z",
        "before": [
          {
            "result": {
              "error_message": "java.lang.NullPointerException: Cannot invoke \"String.hashCode()\" because the return value of \"core.Base.getBrowser()\" is null\r\n\tat core.Base.selectBrowser(Base.java:63)\r\n\tat step.definitions.Initializer.beforeHooks(Initializer.java:19)\r\n",
              "duration": 2997600,
              "status": "failed"
            },
            "match": {
              "location": "step.definitions.Initializer.beforeHooks(io.cucumber.java.Scenario)"
            }
          }
        ],
        "line": 14,
        "name": "User add HP LP 3065 from Desktops tab to the cart",
        "description": "",
        "id": "desktops;user-add-hp-lp-3065-from-desktops-tab-to-the-cart",
        "after": [
          {
            "result": {
              "error_message": "java.lang.NullPointerException: Cannot invoke \"org.openqa.selenium.WebDriver.close()\" because \"core.Base.driver\" is null\r\n\tat core.Base.tearDown(Base.java:58)\r\n\tat step.definitions.Initializer.afterHooks(Initializer.java:27)\r\n",
              "status": "failed"
            },
            "match": {
              "location": "step.definitions.Initializer.afterHooks(io.cucumber.java.Scenario)"
            }
          }
        ],
        "type": "scenario",
        "keyword": "Scenario",
        "steps": [
          {
            "result": {
              "status": "skipped"
            },
            "line": 15,
            "name": "User click ADD TO CART option on ‘HP LP3065’ item",
            "match": {
              "location": "step.definitions.DesktopStepDef.user_click_add_to_cart_option_on_hp_lp3065_item()"
            },
            "keyword": "And "
          },
          {
            "result": {
              "status": "skipped"
            },
            "line": 16,
            "name": "User select quantity 1",
            "match": {
              "arguments": [
                {
                  "val": "1",
                  "offset": 21
                }
              ],
              "location": "step.definitions.DesktopStepDef.user_select_quantity(java.lang.Integer)"
            },
            "keyword": "And "
          },
          {
            "result": {
              "status": "skipped"
            },
            "line": 17,
            "name": "User click add to Cart button",
            "match": {
              "location": "step.definitions.DesktopStepDef.user_click_add_to_cart_button()"
            },
            "keyword": "And "
          },
          {
            "result": {
              "duration": 998400,
              "status": "skipped"
            },
            "line": 18,
            "name": "User should see a message ‘Success: you have added HP LP 3065 to your Shopping cart!’",
            "match": {
              "arguments": [
                {
                  "val": "3065",
                  "offset": 57
                }
              ],
              "location": "step.definitions.DesktopStepDef.user_should_see_a_message_success_you_have_added_hp_lp_to_your_shopping_cart(java.lang.Integer)"
            },
            "keyword": "Then "
          }
        ],
        "tags": [
          {
            "name": "@TestAllDesktops"
          },
          {
            "name": "@AddHP3065"
          }
        ]
      },
      {
        "line": 4,
        "name": "",
        "description": "",
        "type": "background",
        "keyword": "Background",
        "steps": [
          {
            "result": {
              "status": "skipped"
            },
            "line": 5,
            "name": "User is on Retail website",
            "match": {
              "location": "step.definitions.DesktopStepDef.user_is_on_retail_website()"
            },
            "keyword": "Given "
          },
          {
            "result": {
              "status": "skipped"
            },
            "line": 6,
            "name": "User click on Desktops tab",
            "match": {
              "location": "step.definitions.DesktopStepDef.user_click_on_desktops_tab()"
            },
            "keyword": "When "
          },
          {
            "result": {
              "status": "skipped"
            },
            "line": 7,
            "name": "User click on Show all desktops",
            "match": {
              "location": "step.definitions.DesktopStepDef.user_click_on_show_all_desktops()"
            },
            "keyword": "And "
          }
        ]
      },
      {
        "start_timestamp": "2022-05-05T04:06:51.700Z",
        "before": [
          {
            "result": {
              "error_message": "java.lang.NullPointerException: Cannot invoke \"String.hashCode()\" because the return value of \"core.Base.getBrowser()\" is null\r\n\tat core.Base.selectBrowser(Base.java:63)\r\n\tat step.definitions.Initializer.beforeHooks(Initializer.java:19)\r\n",
              "duration": 2997500,
              "status": "failed"
            },
            "match": {
              "location": "step.definitions.Initializer.beforeHooks(io.cucumber.java.Scenario)"
            }
          }
        ],
        "line": 21,
        "name": "User add Canon EOS 5D from Desktops tab to the cart",
        "description": "",
        "id": "desktops;user-add-canon-eos-5d-from-desktops-tab-to-the-cart",
        "after": [
          {
            "result": {
              "error_message": "java.lang.NullPointerException: Cannot invoke \"org.openqa.selenium.WebDriver.close()\" because \"core.Base.driver\" is null\r\n\tat core.Base.tearDown(Base.java:58)\r\n\tat step.definitions.Initializer.afterHooks(Initializer.java:27)\r\n",
              "status": "failed"
            },
            "match": {
              "location": "step.definitions.Initializer.afterHooks(io.cucumber.java.Scenario)"
            }
          }
        ],
        "type": "scenario",
        "keyword": "Scenario",
        "steps": [
          {
            "result": {
              "status": "skipped"
            },
            "line": 22,
            "name": "User click ADD TO CART option on ‘Canon EOS 5D’ item",
            "match": {
              "location": "step.definitions.DesktopStepDef.user_click_add_to_cart_option_on_canon_eos_5d_item()"
            },
            "keyword": "And "
          },
          {
            "result": {
              "status": "skipped"
            },
            "line": 23,
            "name": "User select color from dropdown ‘Red’",
            "match": {
              "location": "step.definitions.DesktopStepDef.user_select_color_from_dropdown_red()"
            },
            "keyword": "And "
          },
          {
            "result": {
              "status": "skipped"
            },
            "line": 24,
            "name": "User select quantity 1",
            "match": {
              "arguments": [
                {
                  "val": "1",
                  "offset": 21
                }
              ],
              "location": "step.definitions.DesktopStepDef.user_select_quantity(java.lang.Integer)"
            },
            "keyword": "And "
          },
          {
            "result": {
              "status": "skipped"
            },
            "line": 25,
            "name": "User click add to Cart button",
            "match": {
              "location": "step.definitions.DesktopStepDef.user_click_add_to_cart_button()"
            },
            "keyword": "And "
          },
          {
            "result": {
              "status": "skipped"
            },
            "line": 26,
            "name": "User should see a message ‘Success: You have added Canon EOS 5D to your shopping cart!’",
            "match": {
              "location": "step.definitions.DesktopStepDef.user_should_see_a_message_success_you_have_added_canon_eos_5d_to_your_shopping_cart()"
            },
            "keyword": "Then "
          }
        ],
        "tags": [
          {
            "name": "@TestAllDesktops"
          },
          {
            "name": "@AddCannon5D"
          }
        ]
      },
      {
        "line": 4,
        "name": "",
        "description": "",
        "type": "background",
        "keyword": "Background",
        "steps": [
          {
            "result": {
              "status": "skipped"
            },
            "line": 5,
            "name": "User is on Retail website",
            "match": {
              "location": "step.definitions.DesktopStepDef.user_is_on_retail_website()"
            },
            "keyword": "Given "
          },
          {
            "result": {
              "status": "skipped"
            },
            "line": 6,
            "name": "User click on Desktops tab",
            "match": {
              "location": "step.definitions.DesktopStepDef.user_click_on_desktops_tab()"
            },
            "keyword": "When "
          },
          {
            "result": {
              "status": "skipped"
            },
            "line": 7,
            "name": "User click on Show all desktops",
            "match": {
              "location": "step.definitions.DesktopStepDef.user_click_on_show_all_desktops()"
            },
            "keyword": "And "
          }
        ]
      },
      {
        "start_timestamp": "2022-05-05T04:06:51.718Z",
        "before": [
          {
            "result": {
              "error_message": "java.lang.NullPointerException: Cannot invoke \"String.hashCode()\" because the return value of \"core.Base.getBrowser()\" is null\r\n\tat core.Base.selectBrowser(Base.java:63)\r\n\tat step.definitions.Initializer.beforeHooks(Initializer.java:19)\r\n",
              "duration": 3998600,
              "status": "failed"
            },
            "match": {
              "location": "step.definitions.Initializer.beforeHooks(io.cucumber.java.Scenario)"
            }
          }
        ],
        "line": 29,
        "name": "User add a review to Canon EOS 5D item in Desktops tab",
        "description": "",
        "id": "desktops;user-add-a-review-to-canon-eos-5d-item-in-desktops-tab",
        "after": [
          {
            "result": {
              "error_message": "java.lang.NullPointerException: Cannot invoke \"org.openqa.selenium.WebDriver.close()\" because \"core.Base.driver\" is null\r\n\tat core.Base.tearDown(Base.java:58)\r\n\tat step.definitions.Initializer.afterHooks(Initializer.java:27)\r\n",
              "duration": 999800,
              "status": "failed"
            },
            "match": {
              "location": "step.definitions.Initializer.afterHooks(io.cucumber.java.Scenario)"
            }
          }
        ],
        "type": "scenario",
        "keyword": "Scenario",
        "steps": [
          {
            "result": {
              "status": "skipped"
            },
            "line": 30,
            "name": "User click on Canon EOS 5D item",
            "match": {
              "location": "step.definitions.DesktopStepDef.user_click_on_canon_eos_5d_item()"
            },
            "keyword": "And "
          },
          {
            "result": {
              "status": "skipped"
            },
            "line": 31,
            "name": "User click on write a review link",
            "match": {
              "location": "step.definitions.DesktopStepDef.user_click_on_write_a_review_link()"
            },
            "keyword": "And "
          },
          {
            "result": {
              "status": "skipped"
            },
            "line": 32,
            "name": "user fill the review information with below information",
            "match": {
              "location": "step.definitions.DesktopStepDef.user_fill_the_review_information_with_below_information(io.cucumber.datatable.DataTable)"
            },
            "rows": [
              {
                "cells": [
                  "yourname",
                  "yourReview",
                  "Rating"
                ]
              },
              {
                "cells": [
                  "name",
                  "review",
                  "Bad or good"
                ]
              }
            ],
            "keyword": "And "
          },
          {
            "result": {
              "duration": 999200,
              "status": "skipped"
            },
            "line": 35,
            "name": "User click on Continue Button",
            "match": {
              "location": "step.definitions.DesktopStepDef.user_click_on_continue_button()"
            },
            "keyword": "And "
          },
          {
            "result": {
              "status": "skipped"
            },
            "line": 36,
            "name": "User should see a message with ‘Thank you for your review. It has been submitted to the webmaster for approval.”",
            "match": {
              "location": "step.definitions.DesktopStepDef.user_should_see_a_message_with_thank_you_for_your_review_it_has_been_submitted_to_the_webmaster_for_approval()"
            },
            "keyword": "Then "
          }
        ],
        "tags": [
          {
            "name": "@TestAllDesktops"
          },
          {
            "name": "@AddReviewCannon"
          }
        ]
      }
    ],
    "name": "Desktops",
    "description": "",
    "id": "desktops",
    "keyword": "Feature",
    "uri": "classpath:feature/Desktop.feature",
    "tags": [
      {
        "name": "@TestAllDesktops",
        "type": "Tag",
        "location": {
          "line": 1,
          "column": 1
        }
      }
    ]
  }
]